mst/netgroup/__init__.py
mst_netgroup-1.2.0.dist-info/METADATA
mst_netgroup-1.2.0.dist-info/WHEEL
mst_netgroup-1.2.0.dist-info/top_level.txt
mst_netgroup-1.2.0.dist-info/RECORD
